dose_instruction_parser/__init__.py
dose_instruction_parser/__main__.py
dose_instruction_parser/di_dosage.py
dose_instruction_parser/di_duration.py
dose_instruction_parser/di_frequency.py
dose_instruction_parser/di_prepare.py
dose_instruction_parser/parser.py
dose_instruction_parser/data/__init__.py
dose_instruction_parser/data/keep_words.txt
dose_instruction_parser/data/replace_words.csv
dose_instruction_parser/tests/__init__.py
dose_instruction_parser/tests/conftest.py
dose_instruction_parser/tests/test_dosage.py
dose_instruction_parser/tests/test_duration.py
dose_instruction_parser/tests/test_frequency.py
dose_instruction_parser/tests/test_parser.py
dose_instruction_parser/tests/test_prepare.py
dose_instruction_parser-2025.1024a0.dist-info/LICENSE
dose_instruction_parser-2025.1024a0.dist-info/METADATA
dose_instruction_parser-2025.1024a0.dist-info/WHEEL
dose_instruction_parser-2025.1024a0.dist-info/entry_points.txt
dose_instruction_parser-2025.1024a0.dist-info/top_level.txt
dose_instruction_parser-2025.1024a0.dist-info/RECORD
