Metadata-Version: 2.2
Name: dose_instruction_parser
Version: 2025.1024a0
Summary: Tool for parsing free text prescription dose instructions into structured output
Author-email: Rosalyn Pearson <rosalyn.pearson@phs.scot>, Nathalie Thureau <nathalie.thureau@phs.scot>, Mark Macartney <mark.macartney@phs.scot>, John Reid <john.reid5@phs.scot>, Johanna Jokio <johanna.jokio@phs.scot>, David Bailey <david.bailey@phs.scot>
License: MIT License
Keywords: prescriptions,dose instructions,medical free text
Classifier: License :: OSI Approved :: MIT License
Classifier: Programming Language :: Python
Classifier: Programming Language :: Python :: 3
Requires-Python: <3.12,>=3.9
License-File: LICENSE
Requires-Dist: spacy<3.5.0,>=3.4.2
Requires-Dist: word2number
Requires-Dist: inflect
Requires-Dist: pyspellchecker<=0.5.5
Requires-Dist: numpy==1.26.4
Requires-Dist: pandas>=2.1.2
Requires-Dist: enlighten>=1.12.4
Provides-Extra: dev
Requires-Dist: colorama; extra == "dev"
Requires-Dist: ipython; extra == "dev"
Requires-Dist: python-dotenv; extra == "dev"
Requires-Dist: pytest; extra == "dev"
Requires-Dist: pytest-cov; extra == "dev"
Requires-Dist: pytest-md-report; extra == "dev"
Requires-Dist: sphinx; extra == "dev"
Requires-Dist: sphinx-autobuild; extra == "dev"
Requires-Dist: sphinx-copybutton; extra == "dev"
Requires-Dist: sphinx_rtd_theme; extra == "dev"
Requires-Dist: bumpver; extra == "dev"
